{
  "schema_version": 1,
  "id": "009-create-eunit-test-suite-for-websocket-transport-er",
  "title": "Create EUnit test suite for WebSocket transport (erlmcp_transport_ws)",
  "section": "transports",
  "state": "researched",
  "overview": "WebSocket transport has 0% test coverage - real-time transport is untested\n\n**Motivation:** WebSocket transport for real-time bidirectional messaging. Critical for browser-based MCP clients.\n\n**Success criteria:**\n- Test file created: apps/erlmcp_transports/test/erlmcp_transport_ws_tests.erl\n- WebSocket protocol tested\n- Coverage ≥80%\n- All tests pass\n\n**Technical constraints:**\n- WebSocket protocol - real WebSocket connections\n- Frame testing - text/binary frames\n- Bidirectional messaging - simultaneous send/receive\n- Error handling - connection drop, invalid frames\n\n**Signals:** priority: high, urgency: P1 - BLOCKS PRODUCTION DEPLOYMENT",
  "branch": null,
  "pr_url": null,
  "pr_number": null,
  "last_error": "Plan quality validation failed:\nMissing required sections: Implementation Plan Title, Implementation Approach",
  "created_at": "2026-01-29T01:31:39.353Z",
  "updated_at": "2026-01-29T16:57:22.653Z",
  "problem_statement": "WebSocket transport has 0% test coverage - real-time transport is untested",
  "motivation": "WebSocket transport for real-time bidirectional messaging. Critical for browser-based MCP clients.",
  "success_criteria": [
    "Test file created: apps/erlmcp_transports/test/erlmcp_transport_ws_tests.erl",
    "WebSocket protocol tested",
    "Coverage ≥80%",
    "All tests pass"
  ],
  "technical_constraints": [
    "WebSocket protocol - real WebSocket connections",
    "Frame testing - text/binary frames",
    "Bidirectional messaging - simultaneous send/receive",
    "Error handling - connection drop, invalid frames"
  ],
  "priority_hint": "high",
  "urgency_hint": "P1 - BLOCKS PRODUCTION DEPLOYMENT"
}
