{
  "schema_version": 1,
  "id": "039-fix-observability-suite-dashboard-failure",
  "title": "Fix Observability Suite Dashboard Failure",
  "section": "ct-fixes",
  "state": "idea",
  "overview": "erlmcp_observability_SUITE fails because dashboard server (Cowboy) can't start - Ranch supervisor not available.\n\n**Motivation:** Observability tests are blocked by missing Ranch startup. Dashboard is important for metrics visualization.\n\n**Success criteria:**\n- Root cause documented (Ranch not started)\n- init_per_suite/1 fixed to start ranch/cowboy\n- Dashboard server starts successfully\n- Observability tests execute\n- rebar3 ct --suite=erlmcp_observability_SUITE runs\n\n**Technical constraints:**\n- Option A: Start ranch in init_per_suite\n- Option B: Make dashboard optional\n- Option C: Start full erlmcp_observability app\n\n**Signals:** priority: critical, urgency: P0 - BLOCKS INTEGRATION TESTING",
  "branch": null,
  "pr_url": null,
  "pr_number": null,
  "last_error": "Research quality validation failed:\nMissing required sections: Research Question, Recommended Approach",
  "created_at": "2026-01-29T04:07:02.828Z",
  "updated_at": "2026-01-29T06:11:27.002Z",
  "problem_statement": "erlmcp_observability_SUITE fails because dashboard server (Cowboy) can't start - Ranch supervisor not available.",
  "motivation": "Observability tests are blocked by missing Ranch startup. Dashboard is important for metrics visualization.",
  "success_criteria": [
    "Root cause documented (Ranch not started)",
    "init_per_suite/1 fixed to start ranch/cowboy",
    "Dashboard server starts successfully",
    "Observability tests execute",
    "rebar3 ct --suite=erlmcp_observability_SUITE runs"
  ],
  "technical_constraints": [
    "Option A: Start ranch in init_per_suite",
    "Option B: Make dashboard optional",
    "Option C: Start full erlmcp_observability app"
  ],
  "priority_hint": "critical",
  "urgency_hint": "P0 - BLOCKS INTEGRATION TESTING"
}
