{
  "schema_version": 1,
  "id": "017-fix-erlmcptransportbehaviorsuite-stdiooptsvalidati",
  "title": "Fix erlmcp_transport_behavior_SUITE stdio_opts_validation failure",
  "section": "ct-fixes",
  "state": "researched",
  "overview": "Transport behavior suite stdio_opts_validation test expects error but gets ok\n\n**Motivation:** Unclear if test expectation is wrong or validation logic is wrong. Must resolve to ensure transport behavior compliance.\n\n**Success criteria:**\n- Root cause documented (validation logic or test expectation)\n- Fix applied (validation or test)\n- stdio_opts_validation test passes\n- All transport behavior tests pass\n- rebar3 ct --suite=erlmcp_transport_behavior_SUITE executes\n\n**Technical constraints:**\n- Must determine if validation is wrong or test expectation is wrong\n- Option A: Fix test to expect ok if validation is correct\n- Option B: Fix validation to reject invalid options if test is correct\n\n**Signals:** priority: critical, urgency: P0 - BLOCKS INTEGRATION TESTING",
  "branch": null,
  "pr_url": null,
  "pr_number": null,
  "last_error": "Plan quality validation failed:\nMissing required sections: Implementation Plan Title, Implementation Approach",
  "created_at": "2026-01-29T01:31:39.356Z",
  "updated_at": "2026-01-29T17:25:07.427Z",
  "problem_statement": "Transport behavior suite stdio_opts_validation test expects error but gets ok",
  "motivation": "Unclear if test expectation is wrong or validation logic is wrong. Must resolve to ensure transport behavior compliance.",
  "success_criteria": [
    "Root cause documented (validation logic or test expectation)",
    "Fix applied (validation or test)",
    "stdio_opts_validation test passes",
    "All transport behavior tests pass",
    "rebar3 ct --suite=erlmcp_transport_behavior_SUITE executes"
  ],
  "technical_constraints": [
    "Must determine if validation is wrong or test expectation is wrong",
    "Option A: Fix test to expect ok if validation is correct",
    "Option B: Fix validation to reject invalid options if test is correct"
  ],
  "priority_hint": "critical",
  "urgency_hint": "P0 - BLOCKS INTEGRATION TESTING"
}
