{
  "schema_version": 1,
  "id": "018-implement-or-remove-15-missing-modules-referenced-",
  "title": "Implement or remove 15+ missing modules referenced by Xref",
  "section": "quality-gates",
  "state": "researched",
  "overview": "60+ undefined function calls to non-existent modules blocking Xref clean state\n\n**Motivation:** Cannot pass Xref quality gate with 60+ undefined calls. Each missing module must be audited - implement if needed, remove references if not needed.\n\n**Success criteria:**\n- All missing modules audited\n- Decision made for each (implement or remove)\n- Needed modules implemented (stubs ok if not critical path)\n- References to unneeded modules removed\n- rebar3 xref shows 0 undefined function calls to missing modules\n\n**Technical constraints:**\n- Must audit each module to determine if needed\n- For modules needed: create stub or full implementation\n- For modules not needed: remove all references\n- Decision matrix includes erlmcp_request_id, erlmcp_tracing, erlmcp_task_manager (NO - replaced by erlmcp_hooks), tcps_persistence, tcps_work_order\n\n**Signals:** priority: high, urgency: P2 - REQUIRED FOR PRODUCTION",
  "branch": null,
  "pr_url": null,
  "pr_number": null,
  "last_error": "Plan quality validation failed:\nMissing required sections: Implementation Plan Title, Implementation Approach",
  "created_at": "2026-01-29T01:31:39.356Z",
  "updated_at": "2026-01-29T17:29:18.947Z",
  "problem_statement": "60+ undefined function calls to non-existent modules blocking Xref clean state",
  "motivation": "Cannot pass Xref quality gate with 60+ undefined calls. Each missing module must be audited - implement if needed, remove references if not needed.",
  "success_criteria": [
    "All missing modules audited",
    "Decision made for each (implement or remove)",
    "Needed modules implemented (stubs ok if not critical path)",
    "References to unneeded modules removed",
    "rebar3 xref shows 0 undefined function calls to missing modules"
  ],
  "technical_constraints": [
    "Must audit each module to determine if needed",
    "For modules needed: create stub or full implementation",
    "For modules not needed: remove all references",
    "Decision matrix includes erlmcp_request_id, erlmcp_tracing, erlmcp_task_manager (NO - replaced by erlmcp_hooks), tcps_persistence, tcps_work_order"
  ],
  "priority_hint": "high",
  "urgency_hint": "P2 - REQUIRED FOR PRODUCTION"
}
